<Properties StartupConfiguration="{1B38CBAE-9EFD-4F4A-AA38-95FC4DD2B083}|Default">
  <MonoDevelop.Ide.DebuggingService.PinnedWatches />
  <Xamarin.Addins.Core.Project ActiveDebugTarget="Android.galaxy_nexus_-_api_33" />
  <MultiItemStartupConfigurations />
  <MonoDevelop.Ide.Workbench ActiveDocument="AluMeet/Views/DirectoryListScreen.xaml">
    <Files>
      <File FileName="AluMeet/Views/PostEventScreen.xaml.cs" Line="23" Column="6" />
      <File FileName="AluMeet/Views/DirectoryListScreen.xaml" Line="32" Column="45" />
      <File FileName="AluMeet/Views/DirectoryListScreen.xaml.cs" Line="20" Column="21" />
      <File FileName="AluMeet/Views/JobListScreen.xaml.cs" Line="14" Column="55" />
      <File FileName="AluMeet/Model/AlumniModel.cs" Line="45" Column="19" />
    </Files>
    <Pads>
      <Pad Id="ProjectPad">
        <State name="__root__">
          <Node name="AluMeet" expanded="True">
            <Node name="AluMeet" expanded="True">
              <Node name="Model" expanded="True" />
              <Node name="Resources" expanded="True">
                <Node name="Images" expanded="True" />
              </Node>
              <Node name="Views" expanded="True" />
              <Node name="App.xaml" expanded="True" />
              <Node name="AppShell.xaml" expanded="True" />
              <Node name="MainPage.xaml" expanded="True" />
            </Node>
          </Node>
        </State>
      </Pad>
    </Pads>
  </MonoDevelop.Ide.Workbench>
  <MonoDevelop.Ide.ItemProperties.AluMeet PreferredExecutionTarget="Android.galaxy_nexus_-_api_33" />
  <MonoDevelop.Ide.Workspace ActiveConfiguration="Debug" />
  <MonoDevelop.Ide.DebuggingService.Breakpoints>
    <BreakpointStore />
  </MonoDevelop.Ide.DebuggingService.Breakpoints>
  <MonoDevelop.MonoDroid LastDeploySdkVersion="33.0.46" />
</Properties>